{"contents": [{"item": "The world is administered by rich but it is constructed by poor.", "owner": "Amit Kalantri, Wealth of Words"}, {"item": "Health is hearty, health is harmony, health is happiness.", "owner": "Amit Kalantri, Wealth of Words"}, {"item": "Respect cannot be inherited, respect is the result of right actions.", "owner": "Amit Kalantri, Wealth of Words"}, {"item": "Education makes your maths better, not necessarily your manners.", "owner": "Amit Kalantri, Wealth of Words"}, {"item": "Music shouldn't be just a tune, it should be a touch.", "owner": "Amit Kalantri, Wealth of Words"}, {"item": "The smell of the sweat is not sweet, but the fruit of the sweat is very sweet.", "owner": "Amit Kalantri, Wealth of Words"}, {"item": "To a farmer dirt is not a waste, it is wealth.", "owner": "Amit Kalantri, Wealth of Words"}, {"item": "I could forget that part, but it had to have been true.", "owner": "Deb Caletti, The Story of Us"}, {"item": "What luck has gave you will probably leave you.", "owner": "Amit Kalantri, Wealth of Words"}, {"item": "In united families, they might sleep with half filled stomach but no one sleeps with empty stomach.", "owner": "Amit Kalantri, Wealth of Words"}, {"item": "A powerful process automatically takes care of progress, productivity and profits.", "owner": "Amit Kalantri, Wealth of Words"}, {"item": "When wealth goes only happiness goes, when health goes even the hope goes.", "owner": "Amit Kalantri, Wealth of Words"}, {"item": "Fashion doesn't make you perfect, but it makes you pretty.", "owner": "Amit Kalantri, Wealth of Words"}, {"item": "You need mountains, long staircases don't make good hikers.", "owner": "Amit Kalantri, Wealth of Words"}, {"item": "We love our mother because she cares and also because she cooks.", "owner": "Amit Kalantri, Wealth of Words"}, {"item": "A professional who doesn't deliver as committed is not just lazy, he is a liar.", "owner": "Amit Kalantri, Wealth of Words"}, {"item": "Story is honorable and trustworthy; plot is shifty, and best kept under house arrest.", "owner": "Stephen King, On Writing: A Memoir of the Craft"}, {"item": "When you were making excuses someone else was making enterprise.", "owner": "Amit Kalantri, Wealth of Words"}, {"item": "The gift of knowledge is empowering, but the gift of wisdom is life-changing.", "owner": "A.D. Posey"}, {"item": "In modern times couples are more concerned about loyalty than love.", "owner": "Amit Kalantri, Wealth of Words"}, {"item": "Fear of failure is fiction, face this fact and fear will fall.", "owner": "Amit Kalantri, Wealth of Words"}, {"item": "Common man's patience will bring him more happiness than common man's power.", "owner": "Amit Kalantri, Wealth of Words"}, {"item": "Power does not pardon, power punishes.", "owner": "Amit Kalantri, Wealth of Words"}, {"item": "You can take the Indian out of the family, but you cannot take the family out of the Indian.", "owner": "Amit Kalantri, Wealth of Words"}, {"item": "A little truth seasons a lie like salt.", "owner": "Jacqueline Carey, Kushiel's Dart"}, {"item": "An old fashioned outfit is not a costume, it's a comedy.", "owner": "Amit Kalantri, Wealth of Words"}, {"item": "Be a true traveller, don't be a temporary tourist.", "owner": "Amit Kalantri"}, {"item": "The sacred-souls of authors are displayed in the beauty of their books.", "owner": "Lailah Gifty Akita, Think Great: Be Great!"}, {"item": "If she says goodbye, someone else will say hi.", "owner": "Amit Kalantri, Wealth of Words"}, {"item": "The salt is to the food, what soul is to the body.", "owner": "Amit Kalantri, Wealth of Words"}, {"item": "Rich can live better than poor but they cannot live without poor.", "owner": "Amit Kalantri, Wealth of Words"}, {"item": "Dresses don't look beautiful on hangers.", "owner": "Amit Kalantri, Wealth of Words"}, {"item": "All worries are less with wine.", "owner": "Amit Kalantri, Wealth of Words"}, {"item": "Before you worry about the beauty of your body, worry about the health of your body.", "owner": "Amit Kalantri, Wealth of Words"}, {"item": "Best of stories are created at Airports, Dinner Tables and Showers!", "owner": "Jasleen Kaur Gumber"}, {"item": "He who sacrifices his respect for love basically burns his body to obtain the light.", "owner": "Amit Kalantri, Wealth of Words"}, {"item": "You cannot choose your face but you can choose your dress.", "owner": "Amit Kalantri, Wealth of Words"}, {"item": "In any game, the game itself is the prize, no matter who wins, ultimately both lose the game.", "owner": "Amit Kalantri, Wealth of Words"}, {"item": "Cowards say it can't be done, critics say it shouldn't have been done, creator say well done.", "owner": "Amit Kalantri, Wealth of Words"}, {"item": "Read a short story every day. By the end of the week you would have read volumes of stories.", "owner": "Lailah Gifty Akita, Think Great: Be Great!"}, {"item": "Principles in a poor is admirable as politeness in a prince.", "owner": "Amit Kalantri, Wealth of Words"}, {"item": "If the farmer is rich, then so is the nation.", "owner": "Amit Kalantri, Wealth of Words"}, {"item": "Every story has a time to be told", "owner": "Haruki Murakami, Sputnik Sweetheart"}, {"item": "Action achieves ambition.", "owner": "Amit Kalantri, Wealth of Words"}, {"item": "Be a worthy worker and work will come.", "owner": "Amit Kalantri, Wealth of Words"}, {"item": "Travelling shouldn't be just a tour, it should be a tale.", "owner": "Amit Kalantri"}, {"item": "With discipline, you can lose weight, you can excel in work, you can win the war.", "owner": "Amit Kalantri, Wealth of Words"}, {"item": "Faster is fatal, slower is safe.", "owner": "Amit Kalantri, Wealth of Words"}, {"item": "Seed becomes tree, son becomes stranger.", "owner": "Amit Kalantri, Wealth of Words"}, {"item": "A farmer is a magician who produces money from the mud.", "owner": "Amit Kalantri, Wealth of Words"}, {"item": "The mistakes of the world are warning message for you.", "owner": "Amit Kalantri, Wealth of Words"}, {"item": "It is the sweat of the servants that make their squire look smart.", "owner": "Amit Kalantri, Wealth of Words"}, {"item": "During a conversation, listening is as powerful as loving.", "owner": "Amit Kalantri, Wealth of Words"}, {"item": "Take care of your costume and your confidence will take care of itself.", "owner": "Amit Kalantri, Wealth of Words"}, {"item": "Hands can cook, hands can create, hands can kill. There is no better tool than our hands.", "owner": "Amit Kalantri, Wealth of Words"}, {"item": "Civilians enjoy their time because soldiers sacrifice their time.", "owner": "Amit Kalantri, Wealth of Words"}, {"item": "Always choose love over fear.", "owner": "A.D. Posey"}, {"item": "Routine ruins the life, variety vitalise the life.", "owner": "Amit Kalantri, Wealth of Words"}, {"item": "Sacrifice of the self is sheer stupidity if sacrifice is not for the self.", "owner": "Amit Kalantri"}, {"item": "A good food is mouthwatering when you see it and finger licking when you eat it.", "owner": "Amit Kalantri, Wealth of Words"}, {"item": "You are never too old to become younger!", "owner": "Mae West"}, {"item": "Seeing the mud around a lotus is pessimism, seeing a lotus in the mud is optimism.", "owner": "Amit Kalantri, Wealth of Words"}, {"item": "Travelling the road will tell you more about the road than the google will tell you about the road.", "owner": "Amit Kalantri"}, {"item": "Trekking means a travelling experience with a thrilling excitement.", "owner": "Amit Kalantri"}, {"item": "Being a writer is a good, good thing.", "owner": "Shannon Hale"}, {"item": "Life is a sea of vibrant color. Jump in.", "owner": "A.D. Posey"}, {"item": "Great losses are great lessons.", "owner": "Amit Kalantri, Wealth of Words"}, {"item": "O' melancholy,hectic chill for human soul,herewith dismal presence,any spirit does descent.", "owner": "Nithin Purple, Halcyon Wings: 'These Passions Feathers Are Gathering on a Winged Vision'"}, {"item": "My spouse is my shield, my spouse is my strength.", "owner": "Amit Kalantri, Wealth of Words"}, {"item": "Music is the fastest motivator in the world.", "owner": "Amit Kalantri, Wealth of Words"}, {"item": "Just because they're a story doesn't mean they're not real.", "owner": "Heather Bouwman, The Remarkable & Very True Story of Lucy & Snowcap"}, {"item": "If thinking should precede acting, then acting must succeed thinking.", "owner": "Amit Kalantri, Wealth of Words"}, {"item": "Don't compare the size of your roof with the size of the sky.", "owner": "Amit Kalantri, Wealth of Words"}, {"item": "How the story will end, no one knows? We can only envisage.", "owner": "Lailah Gifty Akita, Pearls of  Wisdom: Great  mind"}, {"item": "An assembly is extra slow in taking actions.", "owner": "Amit Kalantri, Wealth of Words"}, {"item": "Don't mention your move before you make a move.", "owner": "Amit Kalantri, Wealth of Words"}, {"item": "Writing a story, regardless of length, begins always with a single word.", "owner": "Don Roff"}, {"item": "With right fashion, every female would be a flame.", "owner": "Amit Kalantri, Wealth of Words"}, {"item": "We write to share our thoughts and our lives.", "owner": "Lailah Gifty Akita, Think Great: Be Great!"}, {"item": "A good swordsman is more important than a good sword.", "owner": "Amit Kalantri, Wealth of Words"}, {"item": "Networking isn't how many people you know, it's how many people know you.", "owner": "Amit Kalantri, Wealth of Words"}, {"item": "Fail soon so that you can succeed sooner.", "owner": "Amit Kalantri, Wealth of Words"}, {"item": "Simplicity saves strength.", "owner": "Amit Kalantri, Wealth of Words"}, {"item": "A slip of the foot may injure your body, but a slip of the tongue will injure your bond.", "owner": "Amit Kalantri, Wealth of Words"}, {"item": "Mixing old wine with new wine is stupidity, but mixing old wisdom with new wisdom is maturity.", "owner": "Amit Kalantri, Wealth of Words"}, {"item": "Father has a strengthening character like the sun and mother has a soothing temper like the moon.", "owner": "Amit Kalantri, Wealth of Words"}, {"item": "Passion makes you good, but pride stops you to get better.", "owner": "Amit Kalantri, Wealth of Words"}, {"item": "An entrepreneur with strong network makes money even when he is asleep.", "owner": "Amit Kalantri, Wealth of Words"}, {"item": "Some people when they see cheese, chocolate or cake they don't think of calories.", "owner": "Amit Kalantri, Wealth of Words"}, {"item": "Life is a story, until I awake and saw life as a dream.", "owner": "Lailah Gifty Akita, Pearls of  Wisdom: Great  mind"}], "common_tag": "story,", "updatedAt": "2023-05-26 21:16:05"}