{
    "contents": [
        {
            "item": "Who doesn't desire his father's death?",
            "owner": "Fyodor Dostoyevsky"
        },
        {
            "item": "Insanity is hereditary - you can get it from your children.",
            "owner": "Sam Levenson"
        },
        {
            "item": "Parents are the bones on which children cut their teeth.",
            "owner": "Peter Ustinov"
        },
        {
            "item": "Your children need your presence more than your presents.",
            "owner": "Jesse Jackson"
        },
        {
            "item": "People should be free to find or make for themselves the kinds of educational experiences they want their children to have.",
            "owner": "John Holt"
        },
        {
            "item": "It is the malady of our age that the young are so busy teaching us that they have no time left to learn.",
            "owner": "Eric Hoffer"
        }
    ],
    "pagination": {
        "size": 6,
        "total": 6,
        "current": 5
    }
}